[
  {
    "word": "take down",
    "pos": "phrase",
    "definition": "to write down information, especially something said aloud",
    "example": ["Let me take down your phone number.", "The officer took down every detail of the witness's statement."],
    "synonyms": ["note down", "write down", "record"],
    "topic": "communication",
    "note": "looked up while doing listening practice; in listening it usually means 'to record/note', not 'to dismantle'",
    "first_seen": "2026-05-29",
    "review": { "status": "new", "times_looked_up": 1, "last_seen": "2026-05-29" }
  },
  {
    "word": "mesh",
    "pos": "noun",
    "definition": "material made of a net of wire or thread with small open spaces between",
    "example": ["The window has a fine mesh to keep insects out.", "The bag is made of a light nylon mesh."],
    "synonyms": ["net", "netting"],
    "topic": "daily",
    "note": "looked up during listening practice; can also be a verb meaning 'to fit/work together'",
    "first_seen": "2026-05-29",
    "review": { "status": "new", "times_looked_up": 1, "last_seen": "2026-05-29" }
  },
  {
    "word": "engulf",
    "pos": "verb",
    "definition": "to surround or cover someone or something completely",
    "example": ["Flames quickly engulfed the building.", "She was engulfed by a wave of sadness."],
    "synonyms": ["overwhelm", "swallow up", "submerge"],
    "topic": "nature",
    "note": "looked up during listening practice; often used for fire, water, or strong emotions",
    "first_seen": "2026-05-29",
    "review": { "status": "new", "times_looked_up": 1, "last_seen": "2026-05-29" }
  },
  {
    "word": "in no time",
    "pos": "idiom",
    "definition": "very quickly; in a very short while",
    "example": ["Don't worry, we'll be there in no time.", "With the new tool, the job was done in no time."],
    "synonyms": ["very soon", "quickly", "in a flash"],
    "topic": "daily",
    "note": "looked up during listening practice",
    "first_seen": "2026-05-29",
    "review": { "status": "new", "times_looked_up": 1, "last_seen": "2026-05-29" }
  },
  {
    "word": "brigade",
    "pos": "noun",
    "definition": "a large group of soldiers; also an organized group of people working together",
    "example": ["The fire brigade arrived within minutes.", "An army brigade was sent to the border."],
    "synonyms": ["unit", "team", "squad"],
    "topic": "daily",
    "note": "looked up during listening practice; common in 'fire brigade'",
    "first_seen": "2026-05-29",
    "review": { "status": "new", "times_looked_up": 1, "last_seen": "2026-05-29" }
  },
  {
    "word": "assist",
    "pos": "verb",
    "definition": "to help someone do something",
    "example": ["A nurse assisted the doctor during surgery.", "Can you assist me with this report?"],
    "synonyms": ["help", "aid", "support"],
    "topic": "daily",
    "note": "looked up during listening practice",
    "first_seen": "2026-05-29",
    "review": { "status": "new", "times_looked_up": 1, "last_seen": "2026-05-29" }
  }
]
